rqsession/__init__.py
rqsession/config.ini
rqsession/config_util.py
rqsession/logger.py
rqsession/request_session.py
rqsession/static/language.txt
rqsession/static/proxies.txt
rqsession/static/useragents.txt
rqsession-0.1.0.dist-info/LICENSE
rqsession-0.1.0.dist-info/METADATA
rqsession-0.1.0.dist-info/WHEEL
rqsession-0.1.0.dist-info/RECORD
